{
    "actions": [],
    "allow_rename": 1,
    "creation": "2025-12-21 12:15:00.000000",
    "doctype": "DocType",
    "editable_grid": 1,
    "engine": "InnoDB",
    "field_order": [
        "family_member",
        "first_name",
        "middle_name",
        "last_name",
        "relation",
        "mobile_no",
        "is_visiting",
        "visit_from_date",
        "visit_to_date",
        "visit_date"
    ],
    "fields": [
        {
            "fieldname": "family_member",
            "fieldtype": "Link",
            "label": "Family Member",
            "options": "Family Member"
        },
        {
            "fieldname": "first_name",
            "fieldtype": "Data",
            "in_list_view": 1,
            "label": "First Name",
            "reqd": 1
        },
        {
            "fieldname": "middle_name",
            "fieldtype": "Data",
            "in_list_view": 1,
            "label": "Middle Name"
        },
        {
            "fieldname": "last_name",
            "fieldtype": "Data",
            "in_list_view": 1,
            "label": "Last Name"
        },
        {
            "fieldname": "relation",
            "fieldtype": "Data",
            "in_list_view": 1,
            "label": "Relation"
        },
        {
            "fieldname": "mobile_no",
            "fieldtype": "Data",
            "in_list_view": 1,
            "label": "Mobile No"
        },
        {
            "default": "Yes",
            "fieldname": "is_visiting",
            "fieldtype": "Check",
            "in_list_view": 1,
            "label": "Is Visiting"
        },
        {
            "fieldname": "visit_from_date",
            "fieldtype": "Date",
            "label": "Visit From Date",
            "mandatory_depends_on": "eval:doc.is_visiting==1"
        },
        {
            "fieldname": "visit_to_date",
            "fieldtype": "Date",
            "label": "Visit To Date",
            "mandatory_depends_on": "eval:doc.is_visiting==1"
        },
        {
            "fieldname": "visit_date",
            "fieldtype": "Date",
            "label": "Visit Date"
        }
    ],
    "istable": 1,
    "modified": "2025-12-21 12:15:00.000000",
    "modified_by": "Administrator",
    "module": "Agas",
    "name": "Event Registration Member",
    "owner": "Administrator",
    "permissions": [],
    "sort_field": "modified",
    "sort_order": "DESC",
    "states": []
}
